{
  "airbrush": false,
  "airbrushRate": 20,
  "angle": 0,
  "application": 0,
  "autoBrush": {
    "density": 1,
    "hFade": -1,
    "profile": 0,
    "randomness": 0,
    "softnessCurve": {
      "points": []
    },
    "spikes": 2,
    "vFade": -1
  },
  "autoSpacingCoeff": 1,
  "blendMode": 1,
  "color": "#000000",
  "colorDynamics": {
    "bgColor": "#ffffffff",
    "brightness": 0,
    "enabled": false,
    "fgColor": "#ff000000",
    "hue": 0,
    "purity": 0,
    "saturation": 0
  },
  "dualBrushConfig": {
    "count": 1,
    "enabled": false,
    "hardness": 0.800000011920929,
    "scatter": 0,
    "size": 20,
    "spacing": 1,
    "tipType": 0
  },
  "flipX": false,
  "flipY": false,
  "flow": 0.6000000238418579,
  "flowOption": {
    "combine": 0,
    "enabled": true,
    "maxValue": 1,
    "minValue": 0.6399999856948853,
    "sensors": [
      {
        "curve": {
          "points": [
            [
              0,
              0
            ],
            [
              0.27827586206896526,
              0.14956451910907237
            ],
            [
              1,
              1
            ]
          ]
        },
        "enabled": true,
        "type": 0
      }
    ]
  },
  "group": "Default Brushes/Markers",
  "hardness": 0.4000000059604645,
  "mode": 0,
  "name": "Soft Marker",
  "opacity": 0.699999988079071,
  "opacityOption": {
    "combine": 0,
    "enabled": true,
    "maxValue": 1,
    "minValue": 0.5,
    "sensors": [
      {
        "curve": {
          "points": []
        },
        "enabled": true,
        "type": 0
      }
    ]
  },
  "paintMode": 1,
  "ratioOption": {
    "combine": 0,
    "enabled": false,
    "maxValue": 1,
    "minValue": 0,
    "sensors": []
  },
  "rotationOption": {
    "combine": 0,
    "enabled": false,
    "maxValue": 1,
    "minValue": 0,
    "sensors": []
  },
  "roundness": 0.6000000238418579,
  "scatterAxisX": true,
  "scatterAxisY": true,
  "scatterOption": {
    "combine": 0,
    "enabled": false,
    "maxValue": 1,
    "minValue": 0,
    "sensors": []
  },
  "size": 40,
  "sizeOption": {
    "combine": 0,
    "enabled": false,
    "maxValue": 1,
    "minValue": 0,
    "sensors": []
  },
  "smoothingMode": 0,
  "smoothingRadius": 10,
  "spacing": 0.05000000074505806,
  "textureConfig": {
    "autoInvertForEraser": false,
    "brightness": -0.029999999329447746,
    "contrast": 1.2000000476837158,
    "cutoffMax": 1,
    "cutoffMin": 0,
    "cutoffPolicy": 0,
    "depth": 0.44999998807907104,
    "enabled": true,
    "horizontalOffset": 0,
    "invert": false,
    "neutralPoint": 0.5,
    "randomHorizontalOffset": true,
    "randomVerticalOffset": true,
    "scale": 0.5600000023841858,
    "softTexturing": false,
    "textureId": "fine_paper_grain",
    "texturing": 0,
    "texturingMode": 0,
    "verticalOffset": 0
  },
  "tipBrightness": 0,
  "tipContrast": 0,
  "tipId": "soft_marker",
  "tipImagePath": ":/brushes/tips/soft-flat.png",
  "tipMidpoint": 0.5,
  "tipSource": 1,
  "type": 0,
  "useAutoSpacing": false,
  "wetEdges": false
}
